rootsense/__init__.py
rootsense/__main__.py
rootsense/logs.py
rootsense/osInfo.py
rootsense/performance.py
rootsense/predictive.py
rootsense/report.py
rootsense/root.py
rootsense/thread.py
rootsense/ticket.py
rootsense-0.1.1.dist-info/LICENSE
rootsense-0.1.1.dist-info/METADATA
rootsense-0.1.1.dist-info/WHEEL
rootsense-0.1.1.dist-info/entry_points.txt
rootsense-0.1.1.dist-info/top_level.txt
rootsense-0.1.1.dist-info/RECORD
