Metadata-Version: 2.1
Name: rootsense
Version: 0.1.1
Summary: A system performance and monitoring tool.
Home-page: https://github.com/yourusername/rootsense
Author: Your Name
Author-email: your.email@example.com
License: MIT
Classifier: Programming Language :: Python :: 3
Classifier: License :: OSI Approved :: MIT License
Classifier: Operating System :: OS Independent
Requires-Python: >=3.6
License-File: LICENSE
Requires-Dist: pymongo
Requires-Dist: reportlab
Requires-Dist: psutil
Requires-Dist: pandas
Requires-Dist: numpy
Requires-Dist: scikit-learn
Requires-Dist: statsmodels
Requires-Dist: prophet
